gitee/__init__.py
gitee/auth.py
gitee/client.py
gitee/config.py
gitee/exceptions.py
gitee/utils.py
gitee/resources/__init__.py
gitee/resources/activities.py
gitee/resources/base.py
gitee/resources/checks.py
gitee/resources/emails.py
gitee/resources/enterprises.py
gitee/resources/gists.py
gitee/resources/issues.py
gitee/resources/labels.py
gitee/resources/milestones.py
gitee/resources/misc.py
gitee/resources/organizations.py
gitee/resources/pulls.py
gitee/resources/repositories.py
gitee/resources/search.py
gitee/resources/users.py
gitee/resources/webhooks.py
gitee_openapi-0.2.11.dist-info/LICENSE
gitee_openapi-0.2.11.dist-info/METADATA
gitee_openapi-0.2.11.dist-info/WHEEL
gitee_openapi-0.2.11.dist-info/top_level.txt
gitee_openapi-0.2.11.dist-info/RECORD
